README.rst
setup.cfg
setup.py
Flask_ShellPlus.egg-info/PKG-INFO
Flask_ShellPlus.egg-info/SOURCES.txt
Flask_ShellPlus.egg-info/dependency_links.txt
Flask_ShellPlus.egg-info/not-zip-safe
Flask_ShellPlus.egg-info/pbr.json
Flask_ShellPlus.egg-info/requires.txt
Flask_ShellPlus.egg-info/top_level.txt
flask_shellplus/__init__.py
flask_shellplus/utils.py
tests/__init__.py
tests/test_manage.py