Metadata-Version: 1.1
Name: Flask-ShellPlus
Version: 0.0.2
Summary: UNKNOWN
Home-page: http://github.com/kxxoling/flask-shellplus/
Author: Kane Blueriver
Author-email: kxxoling@gmail.com
License: MIT
Platform: any
Classifier: Environment :: Web Environment
Classifier: Intended Audience :: Developers
Classifier: License :: OSI Approved :: MIT License
Classifier: Operating System :: OS Independent
Classifier: Programming Language :: Python
Classifier: Topic :: Software Development :: Libraries :: Python Modules
